hmd_meta_types/__init__.py
hmd_meta_types/entity.py
hmd_meta_types/utils.py
test/__init__.py
test/conftest.py
test/test_noun.py
test/test_relationship.py
test/test_utils.py
hmd_meta_types-0.2.94.dist-info/METADATA
hmd_meta_types-0.2.94.dist-info/WHEEL
hmd_meta_types-0.2.94.dist-info/top_level.txt
hmd_meta_types-0.2.94.dist-info/RECORD
